quta/__init__.py
quta/allocator.py
quta/constraints.py
quta/thruster.py
quta-0.1.0.dist-info/LICENSE
quta-0.1.0.dist-info/METADATA
quta-0.1.0.dist-info/WHEEL
quta-0.1.0.dist-info/top_level.txt
quta-0.1.0.dist-info/RECORD
