Metadata-Version: 2.1
Name: quta
Version: 0.1.0
Summary: Thrust allocation using Quadratic programming
Home-page: https://github.com/freol35241/quta
Author: Fredrik Olsson
Author-email: freol@outlook.com
Maintainer: Fredrik Olsson
Maintainer-email: freol@outlook.com
License: UNKNOWN
Platform: UNKNOWN
Classifier: Development Status :: 4 - Beta
Classifier: Programming Language :: Python :: 3
Classifier: Operating System :: OS Independent
Classifier: License :: OSI Approved :: MIT License
Requires-Dist: numpy
Requires-Dist: quadprog
